timmytimer/__init__.py
timmytimer-0.2.dist-info/DESCRIPTION.rst
timmytimer-0.2.dist-info/METADATA
timmytimer-0.2.dist-info/RECORD
timmytimer-0.2.dist-info/WHEEL
timmytimer-0.2.dist-info/metadata.json
timmytimer-0.2.dist-info/top_level.txt
