Metadata-Version: 2.0
Name: timmytimer
Version: 0.2
Summary: minimal timer wrapper with print or log
Home-page: https://github.com/hvgab/timmytimer
Author: Henrik V. Gabrielsen
Author-email: henrik.v.gabrielsen+timmytimer@gmail.com
License: MIT
Platform: UNKNOWN
Classifier: Development Status :: 4 - Beta
Classifier: Intended Audience :: Developers
Classifier: License :: OSI Approved :: MIT License
Classifier: Programming Language :: Python
